{
  "selectedItem": "DEXTER GOLD CREATINE",
  "itemData": [
    {
      "Weight": 500
    },
    {
      "Beta Alanine": 12,
      "Vit E": 0.05,
      "Taurine": 1,
      "Caffeine": 0.25,
      "Vit A": 0.05,
      "Carnitine Tartrate": 0.25,
      "Citric Acid": 0.6,
      "Flavour": 0.15,
      "Malto": 0.5,
      "Calcium Silicate": 0.03,
      "Silicon Dioxide": 0.04,
      "Sucralose": 0.1,
      "Ace K": 0.05,
      "Color": 0.001
    },
    {
      "19oz white HDPE ": null,
      " 7.5cc Zipline": null,
      " 1 silica": null,
      "Golden cap 89mm": null,
      " Carton mark19oz12pk": null
    }
  ],
  "totalServings": 15.071,
  "boxes": "432",
  "batch1": "243",
  "batch2": "234",
  "batch3": "",
  "boxElements": [
    "171.99",
    "0.72",
    "14.33",
    "3.58",
    "0.72",
    "3.58",
    "8.60",
    "2.15",
    "7.17",
    "0.43",
    "0.57",
    "1.43",
    "0.72",
    "0.01"
  ],
  "batch1Elements": [
    "193.48",
    "0.81",
    "16.12",
    "4.03",
    "0.81",
    "4.03",
    "9.67",
    "2.42",
    "8.06",
    "0.48",
    "0.64",
    "1.61",
    "0.81",
    "0.02"
  ],
  "batch2Elements": [
    "186.32",
    "0.78",
    "15.53",
    "3.88",
    "0.78",
    "3.88",
    "9.32",
    "2.33",
    "7.76",
    "0.47",
    "0.62",
    "1.55",
    "0.78",
    "0.02"
  ],
  "batch3Elements": [],
  "totalBoxElements": "216.00",
  "totalBatch1Elements": "243.00",
  "totalBatch2Elements": "234.00",
  "totalBatch3Elements": 0
}